{
  "condition_id": "context_only_spec",
  "task_id": "role-permissions-calibration",
  "checkpoint_id": "I05",
  "visible_spec_text": "# Semantic spec for role-permissions-calibration at I05\n\n## SPEC-001: Project owners can edit same-org projects\nCommitment: owner-edit\nIntent: A project owner may edit their own project, and non-owners are denied edit access by default.\nGiven: a non-suspended user and a project in the user's organization\nWhen: the user owns the project and requests edit access\nThen: access is allowed; a non-owner without a role is denied edit access\nScenario:\n- Same-org ownership is sufficient for edit access.\n- A same-org user without ownership or a role cannot edit.\n\n## SPEC-002: Organization admins can edit same-org projects\nCommitment: org-admin-edit\nIntent: A user with an org-level admin role may edit any project in that same organization without removing owner edit behavior.\nGiven: a non-suspended user with an admin role for the project organization\nWhen: the admin requests edit access to a project in that organization\nThen: access is allowed; owner edit behavior remains allowed\nScenario:\n- Org admin edit applies only to projects in the admin's organization.\n- Owner edit from the previous checkpoint remains valid.\n\n## SPEC-003: Viewers can read but cannot edit\nCommitment: viewer-read-only\nIntent: A viewer role grants read access but never edit access, and prior owner/admin edit behavior remains intact.\nGiven: a non-suspended user with a viewer role for the project or organization\nWhen: the viewer requests read or edit access\nThen: read access is allowed and edit access is denied\nScenario:\n- Project viewer and org viewer roles are read-only.\n- Viewer logic must not weaken owner or admin edit rules.\n\n## SPEC-004: Suspended users are denied all access\nCommitment: suspended-users-blocked\nIntent: Suspension denies read and edit access and overrides owner, admin, and viewer permissions.\nGiven: a user with suspended set to true\nWhen: the suspended user requests read or edit access\nThen: access is denied regardless of ownership or roles\nScenario:\n- Suspension blocks both read and edit.\n- Non-suspended users keep prior owner, admin, and viewer behavior.\n\n## SPEC-005: Explicit deny overrides role permissions\nCommitment: explicit-deny-overrides\nIntent: A policy deny for a user, action, and project or organization denies access before allow rules are considered.\nGiven: a policy with an explicit deny matching the user, action, and project or organization\nWhen: the user otherwise has owner, admin, or viewer permission\nThen: access is denied; prior behavior remains unchanged when no deny matches\nScenario:\n- A project-level deny overrides owner/admin/viewer allow rules.\n- An org-level deny overrides same-org role permissions.\n- Non-matching denies do not affect prior behavior.\n",
  "prompt_text": "Task: role-permissions-calibration\nCheckpoint: I05\nCondition: context_only_spec\n\nPublic API contract:\nexport function canAccessProject(input: { user: User; project: Project; action: 'read' | 'edit'; policy?: Policy }): boolean; Policy may include denies, temporaryGrants, and now as an ISO timestamp string.\n\n# Semantic spec for role-permissions-calibration at I05\n\n## SPEC-001: Project owners can edit same-org projects\nCommitment: owner-edit\nIntent: A project owner may edit their own project, and non-owners are denied edit access by default.\nGiven: a non-suspended user and a project in the user's organization\nWhen: the user owns the project and requests edit access\nThen: access is allowed; a non-owner without a role is denied edit access\nScenario:\n- Same-org ownership is sufficient for edit access.\n- A same-org user without ownership or a role cannot edit.\n\n## SPEC-002: Organization admins can edit same-org projects\nCommitment: org-admin-edit\nIntent: A user with an org-level admin role may edit any project in that same organization without removing owner edit behavior.\nGiven: a non-suspended user with an admin role for the project organization\nWhen: the admin requests edit access to a project in that organization\nThen: access is allowed; owner edit behavior remains allowed\nScenario:\n- Org admin edit applies only to projects in the admin's organization.\n- Owner edit from the previous checkpoint remains valid.\n\n## SPEC-003: Viewers can read but cannot edit\nCommitment: viewer-read-only\nIntent: A viewer role grants read access but never edit access, and prior owner/admin edit behavior remains intact.\nGiven: a non-suspended user with a viewer role for the project or organization\nWhen: the viewer requests read or edit access\nThen: read access is allowed and edit access is denied\nScenario:\n- Project viewer and org viewer roles are read-only.\n- Viewer logic must not weaken owner or admin edit rules.\n\n## SPEC-004: Suspended users are denied all access\nCommitment: suspended-users-blocked\nIntent: Suspension denies read and edit access and overrides owner, admin, and viewer permissions.\nGiven: a user with suspended set to true\nWhen: the suspended user requests read or edit access\nThen: access is denied regardless of ownership or roles\nScenario:\n- Suspension blocks both read and edit.\n- Non-suspended users keep prior owner, admin, and viewer behavior.\n\n## SPEC-005: Explicit deny overrides role permissions\nCommitment: explicit-deny-overrides\nIntent: A policy deny for a user, action, and project or organization denies access before allow rules are considered.\nGiven: a policy with an explicit deny matching the user, action, and project or organization\nWhen: the user otherwise has owner, admin, or viewer permission\nThen: access is denied; prior behavior remains unchanged when no deny matches\nScenario:\n- A project-level deny overrides owner/admin/viewer allow rules.\n- An org-level deny overrides same-org role permissions.\n- Non-matching denies do not affect prior behavior.\n\nUse the semantic spec as durable context. No executable feedback assets are provided.\n",
  "executable_feedback_paths": [],
  "feedback_assets": [],
  "public_api_contract": "export function canAccessProject(input: { user: User; project: Project; action: 'read' | 'edit'; policy?: Policy }): boolean; Policy may include denies, temporaryGrants, and now as an ISO timestamp string."
}
